mpl_point_clicker/__init__.py
mpl_point_clicker/_clicker.py
mpl_point_clicker/_version.py
mpl_point_clicker-0.4.1.dist-info/LICENSE
mpl_point_clicker-0.4.1.dist-info/METADATA
mpl_point_clicker-0.4.1.dist-info/WHEEL
mpl_point_clicker-0.4.1.dist-info/top_level.txt
mpl_point_clicker-0.4.1.dist-info/RECORD
