Metadata-Version: 2.1
Name: mpl_point_clicker
Version: 0.4.1
Home-page: https://github.com/ianhi/mpl-point-clicker
Author: Ian Hunt-Isaak
Author-email: ianhuntisaak@gmail.com
License: BSD-3-Clause
Classifier: License :: OSI Approved :: BSD License
License-File: LICENSE
Requires-Dist: matplotlib
Requires-Dist: numpy
Provides-Extra: doc
Requires-Dist: autoapi ; extra == 'doc'
Requires-Dist: furo ; extra == 'doc'
Requires-Dist: numpydoc ; extra == 'doc'
Requires-Dist: sphinx ; extra == 'doc'
Requires-Dist: sphinx-autobuild ; extra == 'doc'
Requires-Dist: sphinx-copybutton ; extra == 'doc'
Requires-Dist: sphinx-gallery >=0.8.2 ; extra == 'doc'
Provides-Extra: test
Requires-Dist: black ; extra == 'test'
Requires-Dist: mpl-playback ; extra == 'test'
Requires-Dist: pytest ; extra == 'test'
Requires-Dist: pytest-mpl ; extra == 'test'
